LICENCE.txt
README.md
setup.cfg
setup.py
sharepoint_api/__init__.py
sharepoint_api/sharepoint_api.py
sharepoint_api.egg-info/PKG-INFO
sharepoint_api.egg-info/SOURCES.txt
sharepoint_api.egg-info/dependency_links.txt
sharepoint_api.egg-info/requires.txt
sharepoint_api.egg-info/top_level.txt